README.md
setup.py
rococo/__init__.py
rococo/auth/__init__.py
rococo/auth/tokens.py
rococo/config/__init__.py
rococo/config/config.py
rococo/data/__init__.py
rococo/data/base.py
rococo/data/mongodb.py
rococo/data/mysql.py
rococo/data/surrealdb.py
rococo/emailing/__init__.py
rococo/emailing/base.py
rococo/emailing/config.py
rococo/emailing/enums.py
rococo/emailing/factory.py
rococo/emailing/mailjet.py
rococo/emailing/ses.py
rococo/messaging/__init__.py
rococo/messaging/base.py
rococo/messaging/rabbitmq.py
rococo/messaging/sqs.py
rococo/models/__init__.py
rococo/models/email.py
rococo/models/login_method.py
rococo/models/organization.py
rococo/models/otp_method.py
rococo/models/person.py
rococo/models/person_organization_role.py
rococo/models/recovery_code.py
rococo/models/versioned_model.py
rococo/models/surrealdb/__init__.py
rococo/models/surrealdb/email.py
rococo/models/surrealdb/login_method.py
rococo/models/surrealdb/organization.py
rococo/models/surrealdb/otp_method.py
rococo/models/surrealdb/person.py
rococo/models/surrealdb/person_organization_role.py
rococo/models/surrealdb/surreal_versioned_model.py
rococo/repositories/__init__.py
rococo/repositories/base_repository.py
rococo/repositories/mongodb/__init__.py
rococo/repositories/mongodb/mongodb_repository.py
rococo/repositories/mysql/__init__.py
rococo/repositories/mysql/mysql_repository.py
rococo/repositories/mysql/organization_repository.py
rococo/repositories/surrealdb/__init__.py
rococo/repositories/surrealdb/organization_repository.py
rococo/repositories/surrealdb/person_organization_role_repository.py
rococo/repositories/surrealdb/surreal_db_repository.py
rococooooo.egg-info/PKG-INFO
rococooooo.egg-info/SOURCES.txt
rococooooo.egg-info/dependency_links.txt
rococooooo.egg-info/requires.txt
rococooooo.egg-info/top_level.txt
tests/__init__.py
tests/base_repository_test.py
tests/config_test.py
tests/model_test.py
tests/mongodb_repository_test.py
tests/surreal_db_repository_test.py